cocotbext/__init__.py
cocotbext/modbus/__init__.py
cocotbext/modbus/error_handling.py
cocotbext/modbus/modbus_bus.py
cocotbext/modbus/modbus_coverage.py
cocotbext/modbus/modbus_driver.py
cocotbext/modbus/modbus_monitor.py
cocotbext/modbus/modbus_rtu.py
cocotbext/modbus/modbus_scoreboard.py
cocotbext_modbus_is4310-0.1.0.dist-info/METADATA
cocotbext_modbus_is4310-0.1.0.dist-info/WHEEL
cocotbext_modbus_is4310-0.1.0.dist-info/top_level.txt
cocotbext_modbus_is4310-0.1.0.dist-info/RECORD
