Metadata-Version: 2.1
Name: cocotbext-modbus-is4310
Version: 0.1.0
Summary: Reusable Verification IP for MODBUS RTU Protocol (IS4310-based) using Cocotb
Home-page: https://github.com/RohithVeer/cocotbext-modbus-rtu
Author: Rohith Mudigonda
Author-email: rohith.mudigonda@example.com
License: UNKNOWN
Platform: UNKNOWN
Classifier: Development Status :: 3 - Alpha
Classifier: Intended Audience :: Developers
Classifier: License :: OSI Approved :: MIT License
Classifier: Programming Language :: Python :: 3
Classifier: Topic :: Scientific/Engineering :: Electronic Design Automation (EDA)
Requires-Python: >=3.7
Requires-Dist: cocotb>=1.7
